naplexer/__init__.py
naplexer/core.py
naplexer/data/1.txt
naplexer/data/2.txt
naplexer/data/3.txt
naplexer/data/4.txt
naplexer/data/5.txt
naplexer/data/6.txt
naplexer-0.1.0.dist-info/METADATA
naplexer-0.1.0.dist-info/WHEEL
naplexer-0.1.0.dist-info/top_level.txt
naplexer-0.1.0.dist-info/RECORD
